pysom/SOM.py
pysom/__init__.py
pysom-0.1.4.dist-info/DESCRIPTION.rst
pysom-0.1.4.dist-info/METADATA
pysom-0.1.4.dist-info/RECORD
pysom-0.1.4.dist-info/WHEEL
pysom-0.1.4.dist-info/metadata.json
pysom-0.1.4.dist-info/top_level.txt
