Metadata-Version: 2.0
Name: pysom
Version: 0.1.4
Summary: Self-organizing Maps,SOM for python
Home-page: https://gitee.com/hoops/pySOM
Author: A.Star
Author-email: chenxiaolong12315@163.com
License: MIT License
Platform: all
Classifier: Development Status :: 4 - Beta
Classifier: Operating System :: OS Independent
Classifier: Intended Audience :: Developers
Classifier: License :: OSI Approved :: MIT License
Classifier: Programming Language :: Python
Classifier: Programming Language :: Python :: Implementation
Classifier: Programming Language :: Python :: 2
Classifier: Programming Language :: Python :: 2.7
Classifier: Programming Language :: Python :: 3
Classifier: Programming Language :: Python :: 3.4
Classifier: Programming Language :: Python :: 3.5
Classifier: Programming Language :: Python :: 3.6
Classifier: Topic :: Software Development :: Libraries
Requires-Dist: matplotlib (>=1.5.1)
Requires-Dist: numpy (>=1.12.0)
Requires-Dist: scipy (>=0.17.1)
